Metadata-Version: 2.1
Name: openwakeword-compact
Version: 0.5.0
Summary: A compact version of the open source framework 'openwakeword' by David Scripka
Home-page: https://github.com/siranshen/openWakeWord-Compact
Author: David Scripka, Siran Shen
Project-URL: Homepage, https://github.com/siranshen/openWakeWord-Compact
Classifier: Programming Language :: Python :: 3
Classifier: License :: OSI Approved :: Apache Software License
Classifier: Operating System :: OS Independent
Requires-Python: >=3.7
Provides-Extra: test
License-File: LICENSE
